{"LMX_LO_HIGH_N_RAW":{"source":"manual","vias":[],"paths":[{"layer":"F.Cu","width":0.35,"points":[[71.25,24.9375],[71.25,26.3],[74.8,26.3],[74.8,27.2],[77.48,27.2],[77.48,26.5]]},{"layer":"F.Cu","width":0.35,"points":[[71.25,26.3],[70.5,26.3],[70.5,21.0],[80.5,21.0],[80.5,24.7],[78.86,24.7]]}]},"LMX_LO_LOW_N_RAW":{"source":"manual","vias":[{"x":72.2,"y":23.0,"diameter":0.45,"drill":0.2},{"x":82.0,"y":24.7,"diameter":0.45,"drill":0.2}],"paths":[{"layer":"F.Cu","width":0.15,"points":[[72.9375,23.75],[72.2,23.0]]},{"layer":"B.Cu","width":0.3,"points":[[72.2,23.0],[82.0,23.0],[82.0,24.7]]},{"layer":"F.Cu","width":0.15,"points":[[82.0,24.7],[81.11,24.7]]},{"layer":"F.Cu","width":0.3,"points":[[81.11,24.7],[81.38,24.97],[81.38,26.5]]}]},"RF_HC_LNA_OUT_RAW":{"source":"manual","vias":[],"paths":[{"layer":"F.Cu","width":0.35,"points":[[80.5,8.875],[79.2,8.875],[79.2,12.62],[80.0,12.62]]}]},"RF_HD_LNA_OUT_RAW":{"source":"manual","vias":[],"paths":[{"layer":"F.Cu","width":0.35,"points":[[110.5,8.875],[109.2,8.875],[109.2,12.62],[110.0,12.62]]}]},"RF_HA_LNA_OUT_RAW":{"source":"manual","vias":[],"paths":[{"layer":"F.Cu","width":0.35,"points":[[20.5,8.875],[15.0,8.875],[15.0,13.2],[20.0,13.2],[20.0,11.925]]}]},"RF_HD_LNA2_IN":{"source":"manual","vias":[],"paths":[{"layer":"F.Cu","width":0.35,"points":[[102.275,13.7],[101.4,14.575],[101.4,17.4],[108.2,17.4],[108.2,15.0],[107.68,15.0],[107.32,14.64],[107.32,13.2]]}]},"RF_HIGH_SWITCHED":{"source":"manual","vias":[],"paths":[{"layer":"F.Cu","width":0.35,"points":[[94.75,14.225],[93.6,13.075],[93.6,10.2],[101.8,10.2],[101.8,16.8],[100.4,16.8],[99.68,16.0]]}]},"RF_HA_IN":{"source":"manual+joint","vias":[],"paths":[{"layer":"F.Cu","width":0.35,"points":[[20.0,7.32],[19.7636,7.32],[19.4056,6.962],[19.4056,6.0944],[20.0,5.5]]},{"layer":"F.Cu","width":0.35,"points":[[20.0,-1.72],[14.0,1.0],[14.0,5.5],[20.0,5.5]]}]},"RF_HB_IN":{"source":"manual+joint","vias":[],"paths":[{"layer":"F.Cu","width":0.35,"points":[[50.0,7.32],[50.2828,7.32],[50.5944,7.0084],[50.5944,6.0944],[50.0,5.5]]},{"layer":"F.Cu","width":0.35,"points":[[50.0,-1.72],[49.35,3.8],[49.35,5.5],[50.0,5.5]]}]},"RF_HC_IN":{"source":"manual+joint","vias":[],"paths":[{"layer":"F.Cu","width":0.35,"points":[[80.0,7.32],[79.0282,8.2918],[77.3882,8.2918],[77.0754,7.979],[77.0754,7.3097],[78.8851,5.5],[80.0,5.5]]},{"layer":"F.Cu","width":0.35,"points":[[80.0,-1.72],[84.0,1.0],[84.0,5.5],[80.0,5.5]]}]},"RF_HD_IN":{"source":"manual+joint","vias":[],"paths":[{"layer":"F.Cu","width":0.35,"points":[[110.0,5.5],[110.5944,6.0944],[110.5944,7.0112],[110.2856,7.32],[110.0,7.32]]},{"layer":"F.Cu","width":0.35,"points":[[110.0,-1.72],[115.0,1.0],[115.0,5.5],[110.0,5.5]]}]},"IF_LOW_SE":{"source":"manual","vias":[{"x":34.3,"y":43.5,"diameter":0.45,"drill":0.2},{"x":73.1,"y":33.65,"diameter":0.45,"drill":0.2}],"paths":[{"layer":"F.Cu","width":0.35,"points":[[35.52,43.5],[34.3,43.5]]},{"layer":"B.Cu","width":0.35,"points":[[34.3,43.5],[34.3,39.5],[69.5,39.5],[73.1,35.9],[73.1,33.65]]},{"layer":"F.Cu","width":0.15,"points":[[73.1,33.65],[72.4,33.65]]}]},"IF_HIGH_SE":{"source":"manual","vias":[{"x":113.5,"y":15.6,"diameter":0.45,"drill":0.2},{"x":70.9,"y":33.65,"diameter":0.45,"drill":0.2}],"paths":[{"layer":"F.Cu","width":0.15,"points":[[111.73,14.41],[112.6,15.6],[113.5,15.6]]},{"layer":"B.Cu","width":0.35,"points":[[113.5,15.6],[113.5,24.0],[73.5,24.0],[72.6,24.9],[70.9,33.65]]},{"layer":"F.Cu","width":0.15,"points":[[70.9,33.65],[71.6,33.65]]}]},"IF_SELECTED":{"source":"manual","vias":[],"paths":[{"layer":"F.Cu","width":0.15,"points":[[72.0,34.35],[72.0,35.2],[76.7,35.2],[77.105,34.0]]}]}}